pyterrier_t5/__init__.py
pyterrier_t5-0.2.1.dist-info/licenses/LICENSE
training/monot5/t5-train-bm25negs.py
training/monot5/t5train.py
pyterrier_t5-0.2.1.dist-info/METADATA
pyterrier_t5-0.2.1.dist-info/WHEEL
pyterrier_t5-0.2.1.dist-info/top_level.txt
pyterrier_t5-0.2.1.dist-info/RECORD
