Metadata-Version: 2.4
Name: pyterrier-t5
Version: 0.2.1
Summary: PyTerrier components for T5 ranking
Author-email: Sean MacAvaney <sean.macavaney@glasgow.ac.uk>
Maintainer-email: Sean MacAvaney <sean.macavaney@glasgow.ac.uk>
Project-URL: Repository, https://github.com/terrierteam/pyterrier_t5
Project-URL: Bug Tracker, https://github.com/terrierteam/pyterrier_t5/issues
Classifier: Programming Language :: Python
Classifier: Operating System :: OS Independent
Classifier: Topic :: Text Processing
Classifier: Topic :: Text Processing :: Indexing
Classifier: License :: OSI Approved :: Mozilla Public License 2.0 (MPL 2.0)
Requires-Python: >=3.9
License-File: LICENSE
Requires-Dist: python-terrier>=0.9.0
Requires-Dist: transformers>=4.0.0
Requires-Dist: torch
Requires-Dist: sentencepiece>=0.1.95
Requires-Dist: pyterrier-alpha
Dynamic: license-file
